py_cui_2048/__init__.py
py_cui_2048/__main__.py
py_cui_2048/game.py
py_cui_2048-0.0.1.dist-info/LICENSE
py_cui_2048-0.0.1.dist-info/METADATA
py_cui_2048-0.0.1.dist-info/WHEEL
py_cui_2048-0.0.1.dist-info/entry_points.txt
py_cui_2048-0.0.1.dist-info/top_level.txt
py_cui_2048-0.0.1.dist-info/RECORD
