Metadata-Version: 2.1
Name: py-cui-2048
Version: 0.0.1
Summary: A command line version of the classic 2048 game, built with py_cui.
Home-page: https://github.com/jwlodek/py_cui_2048
Author: Jakub Wlodek
Author-email: jwlodek.dev@gmail.com
License: BSD 3-Clause
Keywords: tui command-line cli cui curses 2048
Platform: UNKNOWN
Classifier: Development Status :: 3 - Alpha
Classifier: Intended Audience :: Developers
Classifier: Programming Language :: Python :: 3.2
Classifier: Programming Language :: Python :: 3.3
Classifier: Programming Language :: Python :: 3.4
Classifier: Programming Language :: Python :: 3.5
Classifier: Programming Language :: Python :: 3.6
Classifier: Programming Language :: Python :: 3.7
Requires-Dist: py-cui
